{
  "compressionlevel": -1,
  "height": 15,
  "infinite": false,
  "layers": [
    {
      "name": "ground",
      "type": "imagelayer",
      "image": "卫生间.png",
      "x": 0,
      "y": 0,
      "id": 1,
      "visible": true,
      "opacity": 1
    },
    {
      "draworder": "topdown",
      "id": 2,
      "name": "furniture_objects",
      "type": "objectgroup",
      "visible": true,
      "opacity": 1,
      "objects": [
        { "id": 1, "name": "item_01", "type": "furniture", "x": 64, "y": 64, "width": 256, "height": 256 },
        { "id": 2, "name": "item_02", "type": "furniture", "x": 352, "y": 64, "width": 256, "height": 256 },
        { "id": 3, "name": "item_03", "type": "furniture", "x": 64, "y": 192, "width": 256, "height": 256, "properties": [
          { "name": "interactable", "type": "bool", "value": true },
          { "name": "interactSceneId", "type": "string", "value": "interact_bathroom_sink" }
        ]},
        { "id": 4, "name": "item_04", "type": "furniture", "x": 352, "y": 192, "width": 256, "height": 256 },
        { "id": 5, "name": "item_05", "type": "furniture", "x": 192, "y": 64, "width": 256, "height": 256, "properties": [
          { "name": "interactable", "type": "bool", "value": true },
          { "name": "interactSceneId", "type": "string", "value": "interact_bathroom_mirror" }
        ]},
        { "id": 6, "name": "item_06", "type": "furniture", "x": 192, "y": 192, "width": 256, "height": 256 },
        { "id": 7, "name": "item_07", "type": "furniture", "x": 384, "y": 256, "width": 256, "height": 256 },
        { "id": 8, "name": "item_08", "type": "furniture", "x": 32, "y": 256, "width": 256, "height": 256 },
        { "id": 9, "name": "item_09", "type": "furniture", "x": 480, "y": 64, "width": 256, "height": 256 }
      ]
    },
    {
      "draworder": "topdown",
      "id": 3,
      "name": "collision",
      "type": "objectgroup",
      "visible": true,
      "opacity": 1,
      "objects": [
        { "id": 1, "name": "wall_top", "type": "collision", "x": 0, "y": 0, "width": 640, "height": 32 },
        { "id": 2, "name": "wall_bottom", "type": "collision", "x": 0, "y": 448, "width": 640, "height": 32 },
        { "id": 3, "name": "wall_left", "type": "collision", "x": 0, "y": 0, "width": 32, "height": 480 },
        { "id": 4, "name": "wall_right", "type": "collision", "x": 608, "y": 0, "width": 32, "height": 480 }
      ]
    },
    {
      "draworder": "topdown",
      "id": 4,
      "name": "player_spawn",
      "type": "objectgroup",
      "visible": true,
      "opacity": 1,
      "objects": [
        { "id": 1, "name": "spawn_bathroom_door", "type": "spawn", "x": 320, "y": 400, "width": 32, "height": 48 }
      ]
    },
    {
      "draworder": "topdown",
      "id": 5,
      "name": "triggers",
      "type": "objectgroup",
      "visible": true,
      "opacity": 1,
      "objects": [
        {
          "id": 1, "name": "door_livingroom", "type": "door",
          "x": 280, "y": 400, "width": 80, "height": 80,
          "properties": [
            { "name": "triggerType", "type": "string", "value": "walk" },
            { "name": "targetMap", "type": "string", "value": "livingroom" },
            { "name": "targetSpawn", "type": "string", "value": "spawn_from_bathroom" }
          ]
        }
      ]
    },
    {
      "draworder": "topdown",
      "id": 6,
      "name": "npcs",
      "type": "objectgroup",
      "visible": true,
      "opacity": 1,
      "objects": []
    },
    {
      "draworder": "topdown",
      "id": 7,
      "name": "items",
      "type": "objectgroup",
      "visible": true,
      "opacity": 1,
      "objects": []
    }
  ],
  "nextlayerid": 8,
  "nextobjectid": 20,
  "orientation": "orthogonal",
  "renderorder": "right-down",
  "tiledversion": "1.10.2",
  "tileheight": 32,
  "tilesets": [],
  "tilewidth": 32,
  "type": "map",
  "version": "1.10",
  "width": 20
}
